LICENSE.txt
MANIFEST.in
README.rst
setup.cfg
setup.py
tinycrashreporter/.DS_Store
tinycrashreporter/__init__.py
tinycrashreporter/__init__.pyc
tinycrashreporter.egg-info/PKG-INFO
tinycrashreporter.egg-info/SOURCES.txt
tinycrashreporter.egg-info/dependency_links.txt
tinycrashreporter.egg-info/not-zip-safe
tinycrashreporter.egg-info/top_level.txt
tinycrashreporter/__pycache__/__init__.cpython-36.pyc
tinycrashreporter/samples/.DS_Store
tinycrashreporter/samples/CrashyProgram.py
tinycrashreporter/samples/ImportedLibraryOnly.py
tinycrashreporter/tests/CrashTest.py