Metadata-Version: 1.1
Name: tinycrashreporter
Version: 1.0.3
Summary: A Python library to log any exceptions to standard out.
Home-page: https://github.com/tim81cortes/
Author: Tim Aylott
Author-email: tsa29@bath.ac.uk
License: MIT
Keywords: crash report
Platform: UNKNOWN
Classifier: Development Status :: 3 - Alpha
Classifier: Intended Audience :: Developers
Classifier: Topic :: Software Development :: Build Tools
Classifier: License :: OSI Approved :: MIT License
Classifier: Programming Language :: Python :: 3
Classifier: Programming Language :: Python :: 3.3
Classifier: Programming Language :: Python :: 3.4
Classifier: Programming Language :: Python :: 3.5
